jenesis/__init__.py
jenesis/cli.py
jenesis/cmd/__init__.py
jenesis/cmd/add/__init__.py
jenesis/cmd/add/contract.py
jenesis/cmd/add/deployment.py
jenesis/cmd/add/profile.py
jenesis/cmd/attach.py
jenesis/cmd/compile.py
jenesis/cmd/deploy.py
jenesis/cmd/init.py
jenesis/cmd/keys/__init__.py
jenesis/cmd/network.py
jenesis/cmd/new.py
jenesis/cmd/run.py
jenesis/cmd/shell.py
jenesis/cmd/update.py
jenesis/config/__init__.py
jenesis/config/errors.py
jenesis/config/extract.py
jenesis/contracts/__init__.py
jenesis/contracts/build.py
jenesis/contracts/deploy.py
jenesis/contracts/detect.py
jenesis/contracts/monkey.py
jenesis/contracts/observer.py
jenesis/contracts/schema.py
jenesis/keyring/__init__.py
jenesis/keyring/amino/__init__.py
jenesis/keyring/amino/codec.py
jenesis/keyring/errors.py
jenesis/keyring/infos/__init__.py
jenesis/keyring/linux/__init__.py
jenesis/keyring/macos/__init__.py
jenesis/keyring/macos/abi.py
jenesis/keyring/test/__init__.py
jenesis/network/__init__.py
jenesis/tasks/__init__.py
jenesis/tasks/container.py
jenesis/tasks/image.py
jenesis/tasks/monitor.py
jenesis/tasks/utils.py
jenesis-0.7.1.dist-info/LICENSE
jenesis-0.7.1.dist-info/METADATA
jenesis-0.7.1.dist-info/WHEEL
jenesis-0.7.1.dist-info/entry_points.txt
jenesis-0.7.1.dist-info/RECORD
