Metadata-Version: 2.1
Name: jenesis
Version: 0.7.1
Summary: Command line tool for rapid CosmWasm-based smart contract development
License: Apache
Author: Ed FitzGerald
Author-email: edward.fitzgerald@fetch.ai
Requires-Python: >=3.8,<4.0
Classifier: License :: Other/Proprietary License
Classifier: Programming Language :: Python :: 3
Classifier: Programming Language :: Python :: 3.8
Classifier: Programming Language :: Python :: 3.9
Classifier: Programming Language :: Python :: 3.10
Classifier: Programming Language :: Python :: 3.11
Classifier: Programming Language :: Python :: 3.12
Requires-Dist: blessings (>=1.7,<2.0)
Requires-Dist: cosmpy (>=0.9.2,<0.10.0)
Requires-Dist: docker (>=5.0.3,<6.1.0)
Requires-Dist: graphlib-backport (>=1.0.3,<2.0.0)
Requires-Dist: jsonschema (>=4.15.0,<5.0.0)
Requires-Dist: jwskate (>=0.4.1,<0.6.0)
Requires-Dist: keyring (>=23.9.0,<24.0.0)
Requires-Dist: makefun (>=1.15.0,<2.0.0)
Requires-Dist: mkdocs (>=1.3.1,<2.0.0)
Requires-Dist: mkdocs-material (>=8.3.9,<9.0.0)
Requires-Dist: ptpython (>=3.0.23,<4.0.0)
Requires-Dist: toml (>=0.10.2,<0.11.0)
Requires-Dist: tqdm (>=4.64.0,<5.0.0)
